{"name":"Obtaining Ore","description":"To obtain ore, you must kill mobs for them.  All mobs that drop ore will spawn in the overworld.  You can use a few methods to farm ores including through mystical agriculture, and environmental tech void miners.","quests":[{"uuid":"520ecd55-ee5b-40d6-8dfe-b163ca3006d9","name":"Spider","description":"Spiders drop lapis, nickel, and very rarely chicken bait.","x":25,"y":95,"icon":{"id":"minecraft:spawn_egg","nbt":"{EntityTag:{id:\"Spider\"}}"},"tasks":[{"type":"DETECT","longDescription":"Modded ore is more rare than vanilla ore.","items":[{"item":{"id":"minecraft:lapis_ore"}},{"item":{"id":"thermalfoundation:ore","damage":5}}]}],"rewardchoice":[{"id":"minecraft:lapis_block"},{"id":"thermalfoundation:storage","damage":5}],"commandrewards":[]},{"uuid":"b8cec89e-9ee7-493e-9d9b-80985dbda1eb","name":"Creeper","description":"Creepers drop coal, aluminum, and very rarely squid bait.","x":75,"y":21,"icon":{"id":"minecraft:spawn_egg","nbt":"{EntityTag:{id:\"Creeper\"}}"},"tasks":[{"type":"DETECT","longDescription":"Modded ore is more rare than vanilla ore.","items":[{"item":{"id":"minecraft:coal_ore"}},{"item":{"id":"thermalfoundation:ore","damage":4}}]}],"rewardchoice":[{"id":"minecraft:coal_block"},{"id":"thermalfoundation:storage","damage":4}],"commandrewards":[]},{"uuid":"31e96aec-1083-47d6-8dc8-78d4d53980bd","name":"Witch","description":"Witches drop diamond, iridium, and very rarely ocelot bait.","x":123,"y":95,"icon":{"id":"minecraft:spawn_egg","nbt":"{EntityTag:{id:\"Witch\"}}"},"tasks":[{"type":"DETECT","longDescription":"Modded ore is more rare than vanilla ore.","items":[{"item":{"id":"minecraft:diamond_ore"}},{"item":{"id":"thermalfoundation:ore","damage":7}}]}],"rewardchoice":[{"id":"minecraft:diamond_block"},{"id":"thermalfoundation:storage","damage":7}],"commandrewards":[]},{"uuid":"eb06790b-4299-4ce3-94ef-940abc6168ce","name":"Blaze","description":"Blazed drop emerald, platinum, and very rarely wolf bait.","x":25,"y":169,"icon":{"id":"minecraft:spawn_egg","nbt":"{EntityTag:{id:\"Blaze\"}}"},"tasks":[{"type":"DETECT","longDescription":"Modded ore is more rare than vanilla ore.","items":[{"item":{"id":"minecraft:emerald_ore"}},{"item":{"id":"thermalfoundation:ore","damage":6}}]}],"rewardchoice":[{"id":"minecraft:emerald_block"},{"id":"thermalfoundation:storage","damage":6}],"commandrewards":[]},{"uuid":"82cefb76-25e2-4b3d-beab-f625216031f7","name":"Zombie","description":"Zombies drop iron, copper and very rarely cow bait.","x":25,"y":21,"icon":{"id":"minecraft:spawn_egg","nbt":"{EntityTag:{id:\"Zombie\"}}"},"tasks":[{"type":"DETECT","longDescription":"Modded ore is more rare than vanilla ore.","items":[{"item":{"id":"minecraft:iron_ore"}},{"item":{"id":"thermalfoundation:ore"}}]}],"rewardchoice":[{"id":"minecraft:iron_block"},{"id":"thermalfoundation:storage"}],"commandrewards":[]},{"uuid":"dda1d74a-0ed4-44d0-8cfb-413ddc41cc02","name":"Skeleton","description":"Skeletons drop redstone, silver, and very rarely sheep bait.","x":75,"y":95,"icon":{"id":"minecraft:spawn_egg","nbt":"{EntityTag:{id:\"Skeleton\"}}"},"tasks":[{"type":"DETECT","longDescription":"Modded ore is more rare than vanilla ore.","items":[{"item":{"id":"minecraft:redstone_ore"}},{"item":{"id":"thermalfoundation:ore","damage":2}}]}],"rewardchoice":[{"id":"minecraft:redstone_block"},{"id":"thermalfoundation:storage","damage":2}],"commandrewards":[]},{"uuid":"8d736da2-0ca9-4273-817b-a148a79b4c51","name":"Cave Spider","description":"Cave spiders drop quartz and very rarely horse bait.","x":75,"y":169,"icon":{"id":"minecraft:spawn_egg","nbt":"{EntityTag:{id:\"CaveSpider\"}}"},"tasks":[{"type":"DETECT","longDescription":"Modded ore is more rare than vanilla ore.","items":[{"item":{"id":"minecraft:quartz_ore"}}]}],"reward":[{"id":"minecraft:quartz_block"}],"commandrewards":[]},{"uuid":"08bd2dc1-d6ad-4914-b0e9-0d1509692863","name":"Enderman","description":"Endermen drop lead, yellorium and very rarely rabbit bait.","x":123,"y":169,"icon":{"id":"minecraft:spawn_egg","nbt":"{EntityTag:{id:\"Enderman\"}}"},"tasks":[{"type":"DETECT","items":[{"item":{"id":"thermalfoundation:ore","damage":3}},{"item":{"id":"bigreactors:brore"}}]}],"rewardchoice":[{"id":"thermalfoundation:storage","damage":3},{"id":"bigreactors:blockmetals"}],"commandrewards":[]},{"uuid":"d58e40bd-f9f0-457a-801c-8809fd718259","name":"Pigman","description":"Kill pigmen for gold, tin, and very rarely pig bait.","x":123,"y":21,"icon":{"id":"minecraft:spawn_egg","nbt":"{EntityTag:{id:\"PigZombie\"}}"},"tasks":[{"type":"DETECT","longDescription":"Modded ore is more rare than vanilla ore.","items":[{"item":{"id":"minecraft:gold_ore"}},{"item":{"id":"thermalfoundation:ore","damage":1}}]}],"rewardchoice":[{"id":"minecraft:gold_block"},{"id":"thermalfoundation:storage","damage":1}],"commandrewards":[]}],"reputationBar":[]}